vibe/__init__.py
vibe/cli.py
vibe/analyzer/__init__.py
vibe/analyzer/colors.py
vibe/analyzer/radius.py
vibe/analyzer/shadows.py
vibe/analyzer/spacing.py
vibe/analyzer/typography.py
vibe/commands/__init__.py
vibe/commands/check.py
vibe/commands/enforce.py
vibe/commands/init.py
vibe/commands/lock.py
vibe/commands/serve.py
vibe/lock/__init__.py
vibe/lock/generator.py
vibe/lock/schema.py
vibe/mcp/__init__.py
vibe/mcp/server.py
vibe/reporter/__init__.py
vibe/reporter/console.py
vibe/reporter/json_report.py
vibe/reporter/markdown.py
vibe/scanner/__init__.py
vibe/scanner/css.py
vibe/scanner/files.py
vibe/scanner/tailwind.py
vibe/utils/__init__.py
vibe_checkr-0.1.0.dist-info/licenses/LICENSE
vibe_checkr-0.1.0.dist-info/METADATA
vibe_checkr-0.1.0.dist-info/WHEEL
vibe_checkr-0.1.0.dist-info/entry_points.txt
vibe_checkr-0.1.0.dist-info/top_level.txt
vibe_checkr-0.1.0.dist-info/RECORD
