Metadata-Version: 2.4
Name: vibe-checkr
Version: 0.1.0
Summary: Scan, lock, and enforce your design system.
Author-email: Yagiz <hello@vibecheck.dev>
License: MIT
Project-URL: Homepage, https://github.com/ihlamury/vibe-check
Project-URL: Repository, https://github.com/ihlamury/vibe-check
Project-URL: Issues, https://github.com/ihlamury/vibe-check/issues
Keywords: design-system,tailwind,css,linter,design review,ai,vibe-coding,mcp
Classifier: Development Status :: 3 - Alpha
Classifier: Intended Audience :: Developers
Classifier: License :: OSI Approved :: MIT License
Classifier: Programming Language :: Python :: 3
Classifier: Programming Language :: Python :: 3.11
Classifier: Programming Language :: Python :: 3.12
Requires-Python: >=3.11
License-File: LICENSE
Requires-Dist: click>=8.1.0
Requires-Dist: rich>=13.0.0
Requires-Dist: pydantic>=2.0.0
Provides-Extra: dev
Requires-Dist: pytest>=7.0.0; extra == "dev"
Requires-Dist: pytest-cov>=4.0.0; extra == "dev"
Requires-Dist: black>=23.0.0; extra == "dev"
Requires-Dist: ruff>=0.1.0; extra == "dev"
Requires-Dist: mypy>=1.0.0; extra == "dev"
Provides-Extra: mcp
Requires-Dist: mcp>=0.1.0; extra == "mcp"
Dynamic: license-file
